<?xml version='1.0' encoding='UTF-8'?>
<DEFECTS><DEFECT><SFA><FILEPATH>h:\visual studio 2013\projects\n-body simulation barnes-hut algorithm\n-body simulation barnes-hut algorithm\</FILEPATH><FILENAME>nbodyalgorithmbarneshut.cpp</FILENAME><LINE>61</LINE><COLUMN>18</COLUMN></SFA><DEFECTCODE>6244</DEFECTCODE><DESCRIPTION>Local declaration of 'num_threads' hides previous declaration at line '11' of 'h:\visual studio 2013\projects\n-body simulation barnes-hut algorithm\n-body simulation barnes-hut algorithm\nbodyalgorithmbarneshut.cpp'.</DESCRIPTION><FUNCTION>main</FUNCTION><DECORATED>main</DECORATED><FUNCLINE>59</FUNCLINE><PATH><SFA><FILEPATH>h:\visual studio 2013\projects\n-body simulation barnes-hut algorithm\n-body simulation barnes-hut algorithm\</FILEPATH><FILENAME>nbodyalgorithmbarneshut.cpp</FILENAME><LINE>11</LINE><COLUMN>4</COLUMN></SFA></PATH></DEFECT><DEFECT><SFA><FILEPATH>h:\visual studio 2013\projects\n-body simulation barnes-hut algorithm\n-body simulation barnes-hut algorithm\</FILEPATH><FILENAME>nbodyalgorithmbarneshut.cpp</FILENAME><LINE>72</LINE><COLUMN>9</COLUMN></SFA><DEFECTCODE>6246</DEFECTCODE><DESCRIPTION>Local declaration of 'start_time' hides declaration of the same name in outer scope. For additional information, see previous declaration at line '69' of 'h:\visual studio 2013\projects\n-body simulation barnes-hut algorithm\n-body simulation barnes-hut algorithm\nbodyalgorithmbarneshut.cpp'.</DESCRIPTION><FUNCTION>main</FUNCTION><DECORATED>main</DECORATED><FUNCLINE>59</FUNCLINE><PATH><SFA><FILEPATH>h:\visual studio 2013\projects\n-body simulation barnes-hut algorithm\n-body simulation barnes-hut algorithm\</FILEPATH><FILENAME>nbodyalgorithmbarneshut.cpp</FILENAME><LINE>69</LINE><COLUMN>8</COLUMN></SFA></PATH></DEFECT><DEFECT><SFA><FILEPATH>h:\visual studio 2013\projects\n-body simulation barnes-hut algorithm\n-body simulation barnes-hut algorithm\</FILEPATH><FILENAME>nbodyalgorithmbarneshut.cpp</FILENAME><LINE>131</LINE><COLUMN>0</COLUMN></SFA><DEFECTCODE>6993</DEFECTCODE><DESCRIPTION>Code analysis ignores OpenMP constructs; analyzing single-threaded code.</DESCRIPTION><FUNCTION></FUNCTION><DECORATED></DECORATED><FUNCLINE>0</FUNCLINE><PATH/></DEFECT></DEFECTS>